find_where/__init__.py
find_where/finder.py
find_where-1.0.0.dist-info/LICENSE
find_where-1.0.0.dist-info/METADATA
find_where-1.0.0.dist-info/WHEEL
find_where-1.0.0.dist-info/top_level.txt
find_where-1.0.0.dist-info/RECORD
