Metadata-Version: 2.1
Name: find_where
Version: 1.0.0
Summary: find_where is a Python package that provides a function to find values in dictionaries where a specified key matches a given value, similar to filtering in SQL.
Author-email: Daniel Ohnesorge <82357071+danohn@users.noreply.github.com>
License: MIT License
Project-URL: Homepage, https://github.com/danohn/find_where
Keywords: find,where,sql
Classifier: License :: OSI Approved :: MIT License
Classifier: Programming Language :: Python
Classifier: Programming Language :: Python :: 3
Requires-Python: >=3.7
License-File: LICENSE
Provides-Extra: dev
Requires-Dist: pip-tools ; extra == 'dev'
Requires-Dist: pytest ; extra == 'dev'
